BUPT/SICE.py
BUPT/__init__.py
BUPT-10.0.1.dist-info/METADATA
BUPT-10.0.1.dist-info/RECORD
BUPT-10.0.1.dist-info/WHEEL
BUPT-10.0.1.dist-info/top_level.txt
