Metadata-Version: 2.1
Name: BUPT
Version: 10.0.1
Summary: 信息与通信工程学院
Home-page: https://sice.bupt.edu.cn/
Author: BUPTSICE
Author-email: sice@bupt.edu.cn
License: UNKNOWN
Platform: UNKNOWN
Classifier: Programming Language :: Python :: 2
Classifier: Programming Language :: Python :: 3
Classifier: License :: OSI Approved :: MIT License
Classifier: Operating System :: OS Independent
